Advance/full-substractor/substractor.vhd
library ieee;
use ieee.std_logic_1164.all;

entity substractor is
	port(
		x : in std_logic ;
		y : in std_logic ;
		z : in std_logic ;
		d : out std_logic ;
		b : out std_logic 
	);
end entity;

architecture logic of substractor is
	begin
		d <= x xor y xor z;
		b <= (z and (x xnor y)) or (not x and y);
end architecture;

Advance/full-substractor/tb_substractor.vhd
library ieee;
use ieee.std_logic_1164.all;

entity tb_substractor is
end entity;

architecture test of tb_substractor is
	signal X,Y,Z,D,B : std_logic ;
	begin 
		uut : entity work.substractor
			port map(
				x => X,
				y => Y,
				z => Z,
				d => D,
				b => B
			);
		process
			begin 
				X <= '0'; Y <= '0' ; Z <= '0';wait for 10 ns;
				X <= '0'; Y <= '0' ; Z <= '1';wait for 10 ns;
				X <= '0'; Y <= '1' ; Z <= '0';wait for 10 ns;
				X <= '0'; Y <= '1' ; Z <= '1';wait for 10 ns;
				X <= '1'; Y <= '0' ; Z <= '0';wait for 10 ns;
				X <= '1'; Y <= '0' ; Z <= '1';wait for 10 ns;
				X <= '1'; Y <= '1' ; Z <= '0';wait for 10 ns;
				X <= '1'; Y <= '1' ; Z <= '1';wait for 10 ns;
				wait;
		end process;
end architecture;

Advance/full-substractor/wave.vcd
$date
  Tue Nov 04 12:12:38 2025
$end
$version
  GHDL v0
$end
$timescale
  1 fs
$end
$scope module standard $end
$upscope $end
$scope module std_logic_1164 $end
$upscope $end
$scope module tb_substractor $end
$var reg 1 ! x $end
$var reg 1 " y $end
$var reg 1 # z $end
$var reg 1 $ d $end
$var reg 1 % b $end
$scope module uut $end
$var reg 1 & x $end
$var reg 1 ' y $end
$var reg 1 ( z $end
$var reg 1 ) d $end
$var reg 1 * b $end
$upscope $end
$upscope $end
$enddefinitions $end
#0
0!
0"
0#
0$
0%
0&
0'
0(
0)
0*
#10000000
1#
1$
1%
1(
1)
1*
#20000000
1"
0#
1'
0(
#30000000
1#
0$
1(
0)
#40000000
1!
0"
0#
1$
0%
1&
0'
0(
1)
0*
#50000000
1#
0$
1(
0)
#60000000
1"
0#
1'
0(
#70000000
1#
1$
1%
1(
1)
1*
