Advance/8-1_MUX/mux.vhd
library ieee;
use ieee.std_logic_1164.all;

entity mux is
	port(
		s0 , s1,s2:in std_logic ;
		x0,x1,x2,x3,x4,x5,x6,x7:in std_logic ;
		y : out std_logic
	);
end entity;

architecture logic of mux is 
	begin 
		y <=(not s0 and not s1 and not s2 and x0) ---000
					or 
			(not s0 and not s1 and s2 and x1)---001
					or 
			(not s0 and s1 and not s2 and x2) ---010
					or 
			(not s0 and s1 and s2 and x3)---011
					or 
			(s0 and not s1 and not s2 and x4)---100
					or 
			(s0 and not s1 and s2 and x5)---101
					or 
			(s0 and s1 and not s2 and x6)---110
					or 
			(s0 and s1 and s2 and x7);---111
end architecture;

Advance/8-1_MUX/tb_mux.vhd
library ieee;
use ieee.std_logic_1164.all;

entity tb_mux is
end entity;

architecture test of tb_mux is
  signal S0,S1,S2,X0,X1,X2,X3,X4,X5,X6,X7,Y : std_logic;
  begin
    uut: entity work.mux 
      port map(
        s0 => S0,
        s1 => S1,
		s2 => S2,
		x0 => X0,
        x1 => X1,
        x2 => X2,
        x3 => X3,
        x4 => X4,
		x5 => X5,
		x6 => X6,
		x7 => X7,
        y => Y
      );
    process
      begin
		X0 <= '0';X1 <= '0';X2 <= '0';X3 <= '0';X4 <= '0';X5 <= '0';X6 <= '0';X7 <= '0';
        S0 <= '0';S1 <= '0';S2 <= '0';X0 <= '0'; wait for 5 ns; X0 <= '1'; wait for 5 ns;
        
		X0 <= '0';X1 <= '0';X2 <= '0';X3 <= '0';X4 <= '0';X5 <= '0';X6 <= '0';X7 <= '0';
		S0 <= '0';S1 <= '0';S2 <= '1';X1 <= '0'; wait for 5 ns; X1 <= '1'; wait for 5 ns;
		
		X0 <= '0';X1 <= '0';X2 <= '0';X3 <= '0';X4 <= '0';X5 <= '0';X6 <= '0';X7 <= '0';
		S0 <= '0';S1 <= '1';S2 <= '0';X2 <= '0'; wait for 5 ns; X2 <= '1'; wait for 5 ns;
		
		X0 <= '0';X1 <= '0';X2 <= '0';X3 <= '0';X4 <= '0';X5 <= '0';X6 <= '0';X7 <= '0';
		S0 <= '0';S1 <= '1';S2 <= '1';X3 <= '0'; wait for 5 ns; X3 <= '1'; wait for 5 ns;
		
		X0 <= '0';X1 <= '0';X2 <= '0';X3 <= '0';X4 <= '0';X5 <= '0';X6 <= '0';X7 <= '0';
		S0 <= '1';S1 <= '0';S2 <= '0';X4 <= '0'; wait for 5 ns; X4 <= '1'; wait for 5 ns;
		
		X0 <= '0';X1 <= '0';X2 <= '0';X3 <= '0';X4 <= '0';X5 <= '0';X6 <= '0';X7 <= '0';
		S0 <= '1';S1 <= '0';S2 <= '1';X5 <= '0'; wait for 5 ns; X5 <= '1'; wait for 5 ns;
		
		X0 <= '0';X1 <= '0';X2 <= '0';X3 <= '0';X4 <= '0';X5 <= '0';X6 <= '0';X7 <= '0';
		S0 <= '1';S1 <= '1';S2 <= '0';X6 <= '0'; wait for 5 ns; X6 <= '1'; wait for 5 ns;
		
		X0 <= '0';X1 <= '0';X2 <= '0';X3 <= '0';X4 <= '0';X5 <= '0';X6 <= '0';X7 <= '0';
		S0 <= '1';S1 <= '1';S2 <= '1';X7 <= '0'; wait for 5 ns; X7 <= '1'; wait for 5 ns;
        wait;
    end process;
end architecture;

Advance/8-1_MUX/wave.vcd
$date
  Sat Nov 15 18:58:14 2025
$end
$version
  GHDL v0
$end
$timescale
  1 fs
$end
$scope module standard $end
$upscope $end
$scope module std_logic_1164 $end
$upscope $end
$scope module tb_mux $end
$var reg 1 ! s0 $end
$var reg 1 " s1 $end
$var reg 1 # s2 $end
$var reg 1 $ x0 $end
$var reg 1 % x1 $end
$var reg 1 & x2 $end
$var reg 1 ' x3 $end
$var reg 1 ( x4 $end
$var reg 1 ) x5 $end
$var reg 1 * x6 $end
$var reg 1 + x7 $end
$var reg 1 , y $end
$scope module uut $end
$var reg 1 - s0 $end
$var reg 1 . s1 $end
$var reg 1 / s2 $end
$var reg 1 0 x0 $end
$var reg 1 1 x1 $end
$var reg 1 2 x2 $end
$var reg 1 3 x3 $end
$var reg 1 4 x4 $end
$var reg 1 5 x5 $end
$var reg 1 6 x6 $end
$var reg 1 7 x7 $end
$var reg 1 8 y $end
$upscope $end
$upscope $end
$enddefinitions $end
#0
0!
0"
0#
0$
0%
0&
0'
0(
0)
0*
0+
0,
0-
0.
0/
00
01
02
03
04
05
06
07
08
#5000000
1$
1,
10
18
#10000000
1#
0$
0,
1/
00
08
#15000000
1%
1,
11
18
#20000000
1"
0#
0%
0,
1.
0/
01
08
#25000000
1&
1,
12
18
#30000000
1#
0&
0,
1/
02
08
#35000000
1'
1,
13
18
#40000000
1!
0"
0#
0'
0,
1-
0.
0/
03
08
#45000000
1(
1,
14
18
#50000000
1#
0(
0,
1/
04
08
#55000000
1)
1,
15
18
#60000000
1"
0#
0)
0,
1.
0/
05
08
#65000000
1*
1,
16
18
#70000000
1#
0*
0,
1/
06
08
#75000000
1+
1,
17
18
